pvg/__about__.py
pvg/__init__.py
pvg/cli.py
pvg/core.py
pvg/filelist.py
pvg-0.0.2.dist-info/METADATA
pvg-0.0.2.dist-info/WHEEL
pvg-0.0.2.dist-info/entry_points.txt
pvg-0.0.2.dist-info/licenses/LICENSE.txt
pvg-0.0.2.dist-info/RECORD
