Metadata-Version: 2.4
Name: pvg
Version: 0.0.2
Summary: PVG - pip-via-git: Install Python packages directly from Git repositories
Project-URL: Documentation, https://github.com/Hao Wu/pvg#readme
Project-URL: Issues, https://github.com/Hao Wu/pvg/issues
Project-URL: Source, https://github.com/Hao Wu/pvg
Author-email: Hao Wu <haowu@dataset.sh>
License-Expression: MIT
License-File: LICENSE.txt
Keywords: development,git,package manager,pip,pip-via-git
Classifier: Development Status :: 4 - Beta
Classifier: Programming Language :: Python
Classifier: Programming Language :: Python :: 3.8
Classifier: Programming Language :: Python :: 3.9
Classifier: Programming Language :: Python :: 3.10
Classifier: Programming Language :: Python :: 3.11
Classifier: Programming Language :: Python :: 3.12
Classifier: Programming Language :: Python :: Implementation :: CPython
Classifier: Programming Language :: Python :: Implementation :: PyPy
Requires-Python: >=3.8
Requires-Dist: click>=8.0.0
